state-neighbors/state_neighbors.py
state-neighbors/__init__.py
state_neighbors-0.1.2.dist-info/DESCRIPTION.rst
state_neighbors-0.1.2.dist-info/WHEEL
state_neighbors-0.1.2.dist-info/metadata.json
state_neighbors-0.1.2.dist-info/METADATA
state_neighbors-0.1.2.dist-info/RECORD
state_neighbors-0.1.2.dist-info/top_level.txt
state_neighbors/state_neighbors.py
state_neighbors/state_neighbors.csv
state_neighbors/__init__.py
