Metadata-Version: 2.0
Name: state-neighbors
Version: 0.1.2
Summary: Small helper package that allnput and returns a dictionary of all the states that neighbor it.
Home-page: https://github.com/sydhenry/state_neighbors
Author: Sydney Henry
Author-email: shenry@handycodejob.com
License: ISCL
Keywords: state_neighbors
Platform: UNKNOWN
Classifier: Development Status :: 2 - Pre-Alpha
Classifier: Intended Audience :: Developers
Classifier: License :: OSI Approved :: ISC License (ISCL)
Classifier: Natural Language :: English
Classifier: Programming Language :: Python :: 2
Classifier: Programming Language :: Python :: 2.7
Classifier: Programming Language :: Python :: 3
Classifier: Programming Language :: Python :: 3.3
Classifier: Programming Language :: Python :: 3.4
